{
  "id": "00000000-0000-0000-0000-000000000000",
  "prevId": "",
  "version": "7",
  "dialect": "postgresql",
  "tables": {
    "public._prisma_migrations": {
      "name": "_prisma_migrations",
      "schema": "",
      "columns": {
        "id": {
          "name": "id",
          "type": "varchar(36)",
          "primaryKey": true,
          "notNull": true
        },
        "checksum": {
          "name": "checksum",
          "type": "varchar(64)",
          "primaryKey": false,
          "notNull": true
        },
        "finished_at": {
          "name": "finished_at",
          "type": "timestamp with time zone",
          "primaryKey": false,
          "notNull": false
        },
        "migration_name": {
          "name": "migration_name",
          "type": "varchar(255)",
          "primaryKey": false,
          "notNull": true
        },
        "logs": {
          "name": "logs",
          "type": "text",
          "primaryKey": false,
          "notNull": false
        },
        "rolled_back_at": {
          "name": "rolled_back_at",
          "type": "timestamp with time zone",
          "primaryKey": false,
          "notNull": false
        },
        "started_at": {
          "name": "started_at",
          "type": "timestamp with time zone",
          "primaryKey": false,
          "notNull": true,
          "default": "now()"
        },
        "applied_steps_count": {
          "name": "applied_steps_count",
          "type": "integer",
          "primaryKey": false,
          "notNull": true,
          "default": 0
        }
      },
      "indexes": {},
      "foreignKeys": {},
      "compositePrimaryKeys": {},
      "uniqueConstraints": {},
      "checkConstraints": {},
      "policies": {},
      "isRLSEnabled": false
    },
    "public.users": {
      "name": "users",
      "schema": "",
      "columns": {
        "id": {
          "name": "id",
          "type": "text",
          "primaryKey": true,
          "notNull": true
        },
        "username": {
          "name": "username",
          "type": "text",
          "primaryKey": false,
          "notNull": true
        },
        "discriminator": {
          "name": "discriminator",
          "type": "text",
          "primaryKey": false,
          "notNull": false
        },
        "avatarUrl": {
          "name": "avatarUrl",
          "type": "text",
          "primaryKey": false,
          "notNull": false
        },
        "money": {
          "name": "money",
          "type": "integer",
          "primaryKey": false,
          "notNull": true,
          "default": 1000
        },
        "lastDraw": {
          "name": "lastDraw",
          "type": "timestamp(3)",
          "primaryKey": false,
          "notNull": false
        },
        "createdAt": {
          "name": "createdAt",
          "type": "timestamp(3)",
          "primaryKey": false,
          "notNull": true,
          "default": "CURRENT_TIMESTAMP"
        },
        "updatedAt": {
          "name": "updatedAt",
          "type": "timestamp(3)",
          "primaryKey": false,
          "notNull": true
        }
      },
      "indexes": {
        "users_id_key": {
          "name": "users_id_key",
          "columns": [
            {
              "expression": "id",
              "asc": true,
              "nulls": "last",
              "opclass": "text_ops",
              "isExpression": false
            }
          ],
          "isUnique": true,
          "concurrently": false,
          "method": "btree",
          "with": {}
        }
      },
      "foreignKeys": {},
      "compositePrimaryKeys": {},
      "uniqueConstraints": {},
      "checkConstraints": {},
      "policies": {},
      "isRLSEnabled": false
    },
    "public.coin_flip": {
      "name": "coin_flip",
      "schema": "",
      "columns": {
        "id": {
          "name": "id",
          "type": "text",
          "primaryKey": true,
          "notNull": true
        },
        "userId": {
          "name": "userId",
          "type": "text",
          "primaryKey": false,
          "notNull": true
        },
        "bet": {
          "name": "bet",
          "type": "integer",
          "primaryKey": false,
          "notNull": true
        },
        "win": {
          "name": "win",
          "type": "boolean",
          "primaryKey": false,
          "notNull": true
        },
        "updatedMoney": {
          "name": "updatedMoney",
          "type": "integer",
          "primaryKey": false,
          "notNull": true
        },
        "createdAt": {
          "name": "createdAt",
          "type": "timestamp(3)",
          "primaryKey": false,
          "notNull": true,
          "default": "CURRENT_TIMESTAMP"
        }
      },
      "indexes": {
        "coin_flip_id_key": {
          "name": "coin_flip_id_key",
          "columns": [
            {
              "expression": "id",
              "asc": true,
              "nulls": "last",
              "opclass": "text_ops",
              "isExpression": false
            }
          ],
          "isUnique": true,
          "concurrently": false,
          "method": "btree",
          "with": {}
        }
      },
      "foreignKeys": {
        "coin_flip_userId_fkey": {
          "name": "coin_flip_userId_fkey",
          "tableFrom": "coin_flip",
          "tableTo": "users",
          "schemaTo": "public",
          "columnsFrom": [
            "userId"
          ],
          "columnsTo": [
            "id"
          ],
          "onDelete": "restrict",
          "onUpdate": "cascade"
        }
      },
      "compositePrimaryKeys": {},
      "uniqueConstraints": {},
      "checkConstraints": {},
      "policies": {},
      "isRLSEnabled": false
    },
    "public.janken": {
      "name": "janken",
      "schema": "",
      "columns": {
        "id": {
          "name": "id",
          "type": "text",
          "primaryKey": true,
          "notNull": true
        },
        "bet": {
          "name": "bet",
          "type": "boolean",
          "primaryKey": false,
          "notNull": true
        },
        "challengerId": {
          "name": "challengerId",
          "type": "text",
          "primaryKey": false,
          "notNull": true
        },
        "opponentId": {
          "name": "opponentId",
          "type": "text",
          "primaryKey": false,
          "notNull": true
        },
        "challengerHand": {
          "name": "challengerHand",
          "type": "text",
          "primaryKey": false,
          "notNull": true
        },
        "opponentHand": {
          "name": "opponentHand",
          "type": "text",
          "primaryKey": false,
          "notNull": true
        },
        "challengerBet": {
          "name": "challengerBet",
          "type": "integer",
          "primaryKey": false,
          "notNull": false
        },
        "opponentBet": {
          "name": "opponentBet",
          "type": "integer",
          "primaryKey": false,
          "notNull": false
        },
        "winnerUserId": {
          "name": "winnerUserId",
          "type": "text",
          "primaryKey": false,
          "notNull": false
        },
        "createdAt": {
          "name": "createdAt",
          "type": "timestamp(3)",
          "primaryKey": false,
          "notNull": true,
          "default": "CURRENT_TIMESTAMP"
        }
      },
      "indexes": {
        "challenger_id_idx": {
          "name": "challenger_id_idx",
          "columns": [
            {
              "expression": "challengerId",
              "asc": true,
              "nulls": "last",
              "opclass": "text_ops",
              "isExpression": false
            }
          ],
          "isUnique": false,
          "concurrently": false,
          "method": "btree",
          "with": {}
        },
        "janken_id_key": {
          "name": "janken_id_key",
          "columns": [
            {
              "expression": "id",
              "asc": true,
              "nulls": "last",
              "opclass": "text_ops",
              "isExpression": false
            }
          ],
          "isUnique": true,
          "concurrently": false,
          "method": "btree",
          "with": {}
        },
        "opponent_id_idx": {
          "name": "opponent_id_idx",
          "columns": [
            {
              "expression": "opponentId",
              "asc": true,
              "nulls": "last",
              "opclass": "text_ops",
              "isExpression": false
            }
          ],
          "isUnique": false,
          "concurrently": false,
          "method": "btree",
          "with": {}
        }
      },
      "foreignKeys": {
        "janken_challengerId_fkey": {
          "name": "janken_challengerId_fkey",
          "tableFrom": "janken",
          "tableTo": "users",
          "schemaTo": "public",
          "columnsFrom": [
            "challengerId"
          ],
          "columnsTo": [
            "id"
          ],
          "onDelete": "restrict",
          "onUpdate": "cascade"
        },
        "janken_opponentId_fkey": {
          "name": "janken_opponentId_fkey",
          "tableFrom": "janken",
          "tableTo": "users",
          "schemaTo": "public",
          "columnsFrom": [
            "opponentId"
          ],
          "columnsTo": [
            "id"
          ],
          "onDelete": "restrict",
          "onUpdate": "cascade"
        }
      },
      "compositePrimaryKeys": {},
      "uniqueConstraints": {},
      "checkConstraints": {},
      "policies": {},
      "isRLSEnabled": false
    },
    "public.scheduled_messages": {
      "name": "scheduled_messages",
      "schema": "",
      "columns": {
        "id": {
          "name": "id",
          "type": "text",
          "primaryKey": true,
          "notNull": true
        },
        "channelId": {
          "name": "channelId",
          "type": "text",
          "primaryKey": false,
          "notNull": true
        },
        "message": {
          "name": "message",
          "type": "text",
          "primaryKey": false,
          "notNull": true
        },
        "time": {
          "name": "time",
          "type": "text",
          "primaryKey": false,
          "notNull": true
        },
        "createdUserId": {
          "name": "createdUserId",
          "type": "text",
          "primaryKey": false,
          "notNull": true
        },
        "lastUpdatedUserId": {
          "name": "lastUpdatedUserId",
          "type": "text",
          "primaryKey": false,
          "notNull": true
        },
        "isActive": {
          "name": "isActive",
          "type": "boolean",
          "primaryKey": false,
          "notNull": true,
          "default": true
        },
        "createdAt": {
          "name": "createdAt",
          "type": "timestamp(3)",
          "primaryKey": false,
          "notNull": true,
          "default": "CURRENT_TIMESTAMP"
        },
        "updatedAt": {
          "name": "updatedAt",
          "type": "timestamp(3)",
          "primaryKey": false,
          "notNull": true
        },
        "guildId": {
          "name": "guildId",
          "type": "text",
          "primaryKey": false,
          "notNull": true
        }
      },
      "indexes": {
        "scheduled_messages_id_key": {
          "name": "scheduled_messages_id_key",
          "columns": [
            {
              "expression": "id",
              "asc": true,
              "nulls": "last",
              "opclass": "text_ops",
              "isExpression": false
            }
          ],
          "isUnique": true,
          "concurrently": false,
          "method": "btree",
          "with": {}
        }
      },
      "foreignKeys": {
        "scheduled_messages_channelId_fkey": {
          "name": "scheduled_messages_channelId_fkey",
          "tableFrom": "scheduled_messages",
          "tableTo": "guild_channels",
          "schemaTo": "public",
          "columnsFrom": [
            "channelId"
          ],
          "columnsTo": [
            "id"
          ],
          "onDelete": "restrict",
          "onUpdate": "cascade"
        },
        "scheduled_messages_createdUserId_fkey": {
          "name": "scheduled_messages_createdUserId_fkey",
          "tableFrom": "scheduled_messages",
          "tableTo": "users",
          "schemaTo": "public",
          "columnsFrom": [
            "createdUserId"
          ],
          "columnsTo": [
            "id"
          ],
          "onDelete": "restrict",
          "onUpdate": "cascade"
        },
        "scheduled_messages_guildId_fkey": {
          "name": "scheduled_messages_guildId_fkey",
          "tableFrom": "scheduled_messages",
          "tableTo": "guilds",
          "schemaTo": "public",
          "columnsFrom": [
            "guildId"
          ],
          "columnsTo": [
            "id"
          ],
          "onDelete": "restrict",
          "onUpdate": "cascade"
        },
        "scheduled_messages_lastUpdatedUserId_fkey": {
          "name": "scheduled_messages_lastUpdatedUserId_fkey",
          "tableFrom": "scheduled_messages",
          "tableTo": "users",
          "schemaTo": "public",
          "columnsFrom": [
            "lastUpdatedUserId"
          ],
          "columnsTo": [
            "id"
          ],
          "onDelete": "restrict",
          "onUpdate": "cascade"
        }
      },
      "compositePrimaryKeys": {},
      "uniqueConstraints": {},
      "checkConstraints": {},
      "policies": {},
      "isRLSEnabled": false
    },
    "public.guilds": {
      "name": "guilds",
      "schema": "",
      "columns": {
        "id": {
          "name": "id",
          "type": "text",
          "primaryKey": true,
          "notNull": true
        },
        "name": {
          "name": "name",
          "type": "text",
          "primaryKey": false,
          "notNull": true
        },
        "memberCount": {
          "name": "memberCount",
          "type": "integer",
          "primaryKey": false,
          "notNull": true
        },
        "iconUrl": {
          "name": "iconUrl",
          "type": "text",
          "primaryKey": false,
          "notNull": false
        },
        "createdAt": {
          "name": "createdAt",
          "type": "timestamp(3)",
          "primaryKey": false,
          "notNull": true,
          "default": "CURRENT_TIMESTAMP"
        },
        "updatedAt": {
          "name": "updatedAt",
          "type": "timestamp(3)",
          "primaryKey": false,
          "notNull": true
        }
      },
      "indexes": {
        "guilds_id_key": {
          "name": "guilds_id_key",
          "columns": [
            {
              "expression": "id",
              "asc": true,
              "nulls": "last",
              "opclass": "text_ops",
              "isExpression": false
            }
          ],
          "isUnique": true,
          "concurrently": false,
          "method": "btree",
          "with": {}
        }
      },
      "foreignKeys": {},
      "compositePrimaryKeys": {},
      "uniqueConstraints": {},
      "checkConstraints": {},
      "policies": {},
      "isRLSEnabled": false
    },
    "public.guild_channels": {
      "name": "guild_channels",
      "schema": "",
      "columns": {
        "id": {
          "name": "id",
          "type": "text",
          "primaryKey": true,
          "notNull": true
        },
        "guildId": {
          "name": "guildId",
          "type": "text",
          "primaryKey": false,
          "notNull": true
        },
        "name": {
          "name": "name",
          "type": "text",
          "primaryKey": false,
          "notNull": true
        },
        "type": {
          "name": "type",
          "type": "text",
          "primaryKey": false,
          "notNull": true
        }
      },
      "indexes": {
        "guild_channels_id_key": {
          "name": "guild_channels_id_key",
          "columns": [
            {
              "expression": "id",
              "asc": true,
              "nulls": "last",
              "opclass": "text_ops",
              "isExpression": false
            }
          ],
          "isUnique": true,
          "concurrently": false,
          "method": "btree",
          "with": {}
        }
      },
      "foreignKeys": {
        "guild_channels_guildId_fkey": {
          "name": "guild_channels_guildId_fkey",
          "tableFrom": "guild_channels",
          "tableTo": "guilds",
          "schemaTo": "public",
          "columnsFrom": [
            "guildId"
          ],
          "columnsTo": [
            "id"
          ],
          "onDelete": "restrict",
          "onUpdate": "cascade"
        }
      },
      "compositePrimaryKeys": {},
      "uniqueConstraints": {},
      "checkConstraints": {},
      "policies": {},
      "isRLSEnabled": false
    },
    "public.user_settings": {
      "name": "user_settings",
      "schema": "",
      "columns": {
        "userId": {
          "name": "userId",
          "type": "text",
          "primaryKey": false,
          "notNull": true
        },
        "theme": {
          "name": "theme",
          "type": "theme",
          "typeSchema": "public",
          "primaryKey": false,
          "notNull": true,
          "default": "'system'"
        },
        "locale": {
          "name": "locale",
          "type": "text",
          "primaryKey": false,
          "notNull": false
        },
        "published": {
          "name": "published",
          "type": "boolean",
          "primaryKey": false,
          "notNull": true,
          "default": false
        }
      },
      "indexes": {
        "user_settings_userId_key": {
          "name": "user_settings_userId_key",
          "columns": [
            {
              "expression": "userId",
              "asc": true,
              "nulls": "last",
              "opclass": "text_ops",
              "isExpression": false
            }
          ],
          "isUnique": true,
          "concurrently": false,
          "method": "btree",
          "with": {}
        }
      },
      "foreignKeys": {
        "user_settings_userId_fkey": {
          "name": "user_settings_userId_fkey",
          "tableFrom": "user_settings",
          "tableTo": "users",
          "schemaTo": "public",
          "columnsFrom": [
            "userId"
          ],
          "columnsTo": [
            "id"
          ],
          "onDelete": "restrict",
          "onUpdate": "cascade"
        }
      },
      "compositePrimaryKeys": {},
      "uniqueConstraints": {},
      "checkConstraints": {},
      "policies": {},
      "isRLSEnabled": false
    },
    "public.omikuji": {
      "name": "omikuji",
      "schema": "",
      "columns": {
        "id": {
          "name": "id",
          "type": "text",
          "primaryKey": true,
          "notNull": true
        },
        "userId": {
          "name": "userId",
          "type": "text",
          "primaryKey": false,
          "notNull": true
        },
        "result": {
          "name": "result",
          "type": "text",
          "primaryKey": false,
          "notNull": true
        },
        "createdAt": {
          "name": "createdAt",
          "type": "timestamp(3)",
          "primaryKey": false,
          "notNull": true,
          "default": "CURRENT_TIMESTAMP"
        }
      },
      "indexes": {
        "omikuji_id_key": {
          "name": "omikuji_id_key",
          "columns": [
            {
              "expression": "id",
              "asc": true,
              "nulls": "last",
              "opclass": "text_ops",
              "isExpression": false
            }
          ],
          "isUnique": true,
          "concurrently": false,
          "method": "btree",
          "with": {}
        }
      },
      "foreignKeys": {
        "omikuji_userId_fkey": {
          "name": "omikuji_userId_fkey",
          "tableFrom": "omikuji",
          "tableTo": "users",
          "schemaTo": "public",
          "columnsFrom": [
            "userId"
          ],
          "columnsTo": [
            "id"
          ],
          "onDelete": "restrict",
          "onUpdate": "cascade"
        }
      },
      "compositePrimaryKeys": {},
      "uniqueConstraints": {},
      "checkConstraints": {},
      "policies": {},
      "isRLSEnabled": false
    },
    "public.guild_roles": {
      "name": "guild_roles",
      "schema": "",
      "columns": {
        "id": {
          "name": "id",
          "type": "text",
          "primaryKey": true,
          "notNull": true
        },
        "guildId": {
          "name": "guildId",
          "type": "text",
          "primaryKey": false,
          "notNull": true
        },
        "name": {
          "name": "name",
          "type": "text",
          "primaryKey": false,
          "notNull": true
        },
        "color": {
          "name": "color",
          "type": "text",
          "primaryKey": false,
          "notNull": true
        },
        "hoist": {
          "name": "hoist",
          "type": "boolean",
          "primaryKey": false,
          "notNull": true
        },
        "position": {
          "name": "position",
          "type": "integer",
          "primaryKey": false,
          "notNull": true
        },
        "permissions": {
          "name": "permissions",
          "type": "text",
          "primaryKey": false,
          "notNull": true
        },
        "managed": {
          "name": "managed",
          "type": "boolean",
          "primaryKey": false,
          "notNull": true
        },
        "mentionable": {
          "name": "mentionable",
          "type": "boolean",
          "primaryKey": false,
          "notNull": true
        }
      },
      "indexes": {
        "guild_roles_id_key": {
          "name": "guild_roles_id_key",
          "columns": [
            {
              "expression": "id",
              "asc": true,
              "nulls": "last",
              "opclass": "text_ops",
              "isExpression": false
            }
          ],
          "isUnique": true,
          "concurrently": false,
          "method": "btree",
          "with": {}
        }
      },
      "foreignKeys": {
        "guild_roles_guildId_fkey": {
          "name": "guild_roles_guildId_fkey",
          "tableFrom": "guild_roles",
          "tableTo": "guilds",
          "schemaTo": "public",
          "columnsFrom": [
            "guildId"
          ],
          "columnsTo": [
            "id"
          ],
          "onDelete": "restrict",
          "onUpdate": "cascade"
        }
      },
      "compositePrimaryKeys": {},
      "uniqueConstraints": {},
      "checkConstraints": {},
      "policies": {},
      "isRLSEnabled": false
    },
    "public.chat_threads": {
      "name": "chat_threads",
      "schema": "",
      "columns": {
        "id": {
          "name": "id",
          "type": "text",
          "primaryKey": true,
          "notNull": true
        },
        "title": {
          "name": "title",
          "type": "text",
          "primaryKey": false,
          "notNull": false
        },
        "guildId": {
          "name": "guildId",
          "type": "text",
          "primaryKey": false,
          "notNull": true
        },
        "channelId": {
          "name": "channelId",
          "type": "text",
          "primaryKey": false,
          "notNull": true
        },
        "creatorId": {
          "name": "creatorId",
          "type": "text",
          "primaryKey": false,
          "notNull": true
        },
        "isActive": {
          "name": "isActive",
          "type": "boolean",
          "primaryKey": false,
          "notNull": true,
          "default": true
        },
        "createdAt": {
          "name": "createdAt",
          "type": "timestamp(3)",
          "primaryKey": false,
          "notNull": true,
          "default": "CURRENT_TIMESTAMP"
        },
        "updatedAt": {
          "name": "updatedAt",
          "type": "timestamp(3)",
          "primaryKey": false,
          "notNull": true
        }
      },
      "indexes": {
        "channel_id_idx": {
          "name": "channel_id_idx",
          "columns": [
            {
              "expression": "channelId",
              "asc": true,
              "nulls": "last",
              "opclass": "text_ops",
              "isExpression": false
            }
          ],
          "isUnique": false,
          "concurrently": false,
          "method": "btree",
          "with": {}
        },
        "chat_threads_id_key": {
          "name": "chat_threads_id_key",
          "columns": [
            {
              "expression": "id",
              "asc": true,
              "nulls": "last",
              "opclass": "text_ops",
              "isExpression": false
            }
          ],
          "isUnique": true,
          "concurrently": false,
          "method": "btree",
          "with": {}
        }
      },
      "foreignKeys": {
        "chat_threads_creatorId_fkey": {
          "name": "chat_threads_creatorId_fkey",
          "tableFrom": "chat_threads",
          "tableTo": "users",
          "schemaTo": "public",
          "columnsFrom": [
            "creatorId"
          ],
          "columnsTo": [
            "id"
          ],
          "onDelete": "restrict",
          "onUpdate": "cascade"
        }
      },
      "compositePrimaryKeys": {},
      "uniqueConstraints": {},
      "checkConstraints": {},
      "policies": {},
      "isRLSEnabled": false
    },
    "public.chat_messages": {
      "name": "chat_messages",
      "schema": "",
      "columns": {
        "id": {
          "name": "id",
          "type": "text",
          "primaryKey": true,
          "notNull": true
        },
        "threadId": {
          "name": "threadId",
          "type": "text",
          "primaryKey": false,
          "notNull": true
        },
        "content": {
          "name": "content",
          "type": "text",
          "primaryKey": false,
          "notNull": true
        },
        "role": {
          "name": "role",
          "type": "ChatRole",
          "typeSchema": "public",
          "primaryKey": false,
          "notNull": true
        },
        "tokenCount": {
          "name": "tokenCount",
          "type": "integer",
          "primaryKey": false,
          "notNull": true
        },
        "createdAt": {
          "name": "createdAt",
          "type": "timestamp(3)",
          "primaryKey": false,
          "notNull": true,
          "default": "CURRENT_TIMESTAMP"
        }
      },
      "indexes": {
        "chat_messages_id_key": {
          "name": "chat_messages_id_key",
          "columns": [
            {
              "expression": "id",
              "asc": true,
              "nulls": "last",
              "opclass": "text_ops",
              "isExpression": false
            }
          ],
          "isUnique": true,
          "concurrently": false,
          "method": "btree",
          "with": {}
        },
        "thread_id_idx": {
          "name": "thread_id_idx",
          "columns": [
            {
              "expression": "threadId",
              "asc": true,
              "nulls": "last",
              "opclass": "text_ops",
              "isExpression": false
            }
          ],
          "isUnique": false,
          "concurrently": false,
          "method": "btree",
          "with": {}
        }
      },
      "foreignKeys": {
        "chat_messages_threadId_fkey": {
          "name": "chat_messages_threadId_fkey",
          "tableFrom": "chat_messages",
          "tableTo": "chat_threads",
          "schemaTo": "public",
          "columnsFrom": [
            "threadId"
          ],
          "columnsTo": [
            "id"
          ],
          "onDelete": "cascade",
          "onUpdate": "cascade"
        }
      },
      "compositePrimaryKeys": {},
      "uniqueConstraints": {},
      "checkConstraints": {},
      "policies": {},
      "isRLSEnabled": false
    },
    "public.guild_members": {
      "name": "guild_members",
      "schema": "",
      "columns": {
        "guildId": {
          "name": "guildId",
          "type": "text",
          "primaryKey": false,
          "notNull": true
        },
        "userId": {
          "name": "userId",
          "type": "text",
          "primaryKey": false,
          "notNull": true
        },
        "nickname": {
          "name": "nickname",
          "type": "text",
          "primaryKey": false,
          "notNull": false
        },
        "joinedAt": {
          "name": "joinedAt",
          "type": "timestamp(3)",
          "primaryKey": false,
          "notNull": true
        }
      },
      "indexes": {},
      "foreignKeys": {
        "guild_members_guildId_fkey": {
          "name": "guild_members_guildId_fkey",
          "tableFrom": "guild_members",
          "tableTo": "guilds",
          "schemaTo": "public",
          "columnsFrom": [
            "guildId"
          ],
          "columnsTo": [
            "id"
          ],
          "onDelete": "restrict",
          "onUpdate": "cascade"
        },
        "guild_members_userId_fkey": {
          "name": "guild_members_userId_fkey",
          "tableFrom": "guild_members",
          "tableTo": "users",
          "schemaTo": "public",
          "columnsFrom": [
            "userId"
          ],
          "columnsTo": [
            "id"
          ],
          "onDelete": "restrict",
          "onUpdate": "cascade"
        }
      },
      "compositePrimaryKeys": {
        "guild_members_pkey": {
          "name": "guild_members_pkey",
          "columns": [
            "guildId",
            "userId"
          ]
        }
      },
      "uniqueConstraints": {},
      "checkConstraints": {},
      "policies": {},
      "isRLSEnabled": false
    }
  },
  "enums": {
    "public.ChatRole": {
      "name": "ChatRole",
      "values": [
        "SYSTEM",
        "USER",
        "ASSISTANT"
      ],
      "schema": "public"
    },
    "public.theme": {
      "name": "theme",
      "values": [
        "system",
        "light",
        "dark"
      ],
      "schema": "public"
    }
  },
  "schemas": {},
  "sequences": {},
  "roles": {},
  "policies": {},
  "views": {},
  "_meta": {
    "schemas": {},
    "tables": {},
    "columns": {}
  },
  "internal": {
    "tables": {}
  }
}